rubik_impl.py
rubik_impl-0.4.dist-info/METADATA
rubik_impl-0.4.dist-info/WHEEL
rubik_impl-0.4.dist-info/licenses/LICENSE
rubik_impl-0.4.dist-info/RECORD
