Metadata-Version: 2.4
Name: rubik_impl
Version: 0.4
Summary: Implementation of Rubik's cube moves
Author-email: RadoTheProgrammer <rrrado15@gmail.com>
License-Expression: MIT
License-File: LICENSE
Classifier: Operating System :: OS Independent
Classifier: Programming Language :: Python :: 3
Requires-Python: >=3.13
Requires-Dist: numpy>=2.2.5
